upiano/__init__.py
upiano/app.py
upiano/keyboard_ui.py
upiano/legacy.py
upiano/midi.py
upiano/note_render.py
upiano/piano.py
upiano/soundfonts/GeneralUser_GS_v1.471.sf2
upiano/style.css
upiano/widgets.py
upiano-0.1.2.dist-info/METADATA
upiano-0.1.2.dist-info/WHEEL
upiano-0.1.2.dist-info/entry_points.txt
upiano-0.1.2.dist-info/RECORD
