Metadata-Version: 2.1
Name: upiano
Version: 0.1.2
Summary: Terminal Piano App
License: MIT
Author: Elias Dorneles
Author-email: elias.dorneles@hey.com
Requires-Python: >=3.10,<4.0
Classifier: License :: OSI Approved :: MIT License
Classifier: Programming Language :: Python :: 3
Classifier: Programming Language :: Python :: 3.10
Classifier: Programming Language :: Python :: 3.11
Requires-Dist: pyFluidSynth (>=1.3.2,<2.0.0)
Requires-Dist: textual (>=0.32.0,<0.33.0)
